{"stats":{"minecraft:used":{"minecraft:trident":1,"minecraft:netherite_sword":60},"minecraft:killed":{"minecraft:spider":1,"minecraft:drowned":1,"minecraft:warden":1},"minecraft:custom":{"minecraft:jump":78,"minecraft:time_since_rest":8478,"minecraft:leave_game":1,"minecraft:damage_dealt":5291,"minecraft:walk_on_water_one_cm":175,"minecraft:sprint_one_cm":3915,"minecraft:play_time":8478,"minecraft:time_since_death":8478,"minecraft:walk_one_cm":3140,"minecraft:sneak_time":106,"minecraft:total_world_time":11009,"minecraft:walk_under_water_one_cm":983,"minecraft:mob_kills":3,"minecraft:fly_one_cm":34522},"minecraft:picked_up":{"minecraft:rotten_flesh":2,"minecraft:leather":1}},"DataVersion":3465}